<?xml version="1.0" encoding="utf-8"?>
<!DOCTYPE hibernate-mapping PUBLIC "-//Hibernate/Hibernate Mapping DTD 3.0//EN"
"http://hibernate.sourceforge.net/hibernate-mapping-3.0.dtd">
<!-- 
    Mapping file autogenerated by MyEclipse Persistence Tools
-->
<hibernate-mapping>
    <class name="cn.digitalpublishing.ep.po.BUrl" table="epub_b_url">
        <id name="id" type="java.lang.String">
            <column name="URL_ID" length="32" />
            <generator class="uuid.hex" />
        </id>       
        <property name="url" type="java.lang.String">
            <column name="URL" length="128">
            	<comment>URL</comment>
            </column>
        </property>  
        <set name="uuRelations" inverse="true">
            <key>
                <column name="URL_ID" length="32" />
            </key>
            <one-to-many class="cn.digitalpublishing.ep.po.BUuRelation" />
        </set>      
    </class>
</hibernate-mapping>
